dbToolBox/dbToolBox.py
ChipDataDbToolbox-1.0.0.dist-info/LICENSE
ChipDataDbToolbox-1.0.0.dist-info/METADATA
ChipDataDbToolbox-1.0.0.dist-info/WHEEL
ChipDataDbToolbox-1.0.0.dist-info/top_level.txt
ChipDataDbToolbox-1.0.0.dist-info/RECORD
